downloadunzip/LICENSE
downloadunzip/README.MD
downloadunzip/__init__.py
downloadunzip/requirements.txt
downloadunzip/thirdparty.json
downloadunzip-0.10.dist-info/LICENSE.rst
downloadunzip-0.10.dist-info/METADATA
downloadunzip-0.10.dist-info/WHEEL
downloadunzip-0.10.dist-info/top_level.txt
downloadunzip-0.10.dist-info/RECORD
