Metadata-Version: 2.1
Name: downloadunzip
Version: 0.10
Summary: creates, uploads, downloads, extracts and copies archives (zip, tar ...)
Home-page: https://github.com/hansalemaos/downloadunzip
Author: Johannes Fischer
Author-email: <aulasparticularesdealemaosp@gmail.com>
License: MIT
Keywords: zip,tar.gz,pack,unpack
Classifier: Development Status :: 4 - Beta
Classifier: Programming Language :: Python :: 3 :: Only
Classifier: Programming Language :: Python :: 3.10
Classifier: Topic :: Scientific/Engineering :: Visualization
Classifier: Topic :: Software Development :: Libraries :: Python Modules
Classifier: Topic :: Utilities
License-File: LICENSE.rst
Requires-Dist: FastCopyFast
Requires-Dist: list-all-files-recursively
Requires-Dist: requests
Requires-Dist: touchtouch
